jobtailor/__init__.py
jobtailor/prompts/extract-coverletter.txt
jobtailor/prompts/extract-job.txt
jobtailor/prompts/extract-resume.txt
jobtailor/prompts/persona.txt
jobtailor/prompts/tailored-experience.txt
jobtailor/prompts/tailored-projects.txt
jobtailor/prompts/tailored-skills.txt
jobtailor/resources/jakes_template.tex
jobtailor/resources/jobtailor-coverletter.docx
jobtailor/utils/__init__.py
jobtailor/utils/functions.py
jobtailor-0.1.5.dist-info/LICENSE
jobtailor-0.1.5.dist-info/METADATA
jobtailor-0.1.5.dist-info/WHEEL
jobtailor-0.1.5.dist-info/top_level.txt
jobtailor-0.1.5.dist-info/RECORD
