Metadata-Version: 2.1
Name: jobtailor
Version: 0.1.5
License-File: LICENSE
Requires-Dist: python-dotenv
Requires-Dist: google.generativeai
Requires-Dist: PyPDF2
Requires-Dist: jinja2
Requires-Dist: python-docx
